msgspec/__init__.py
msgspec/__init__.pyi
msgspec/_core.cp314t-win_amd64.pyd
msgspec/_json_schema.py
msgspec/_utils.py
msgspec/_version.py
msgspec/inspect.py
msgspec/json.py
msgspec/json.pyi
msgspec/msgpack.py
msgspec/msgpack.pyi
msgspec/py.typed
msgspec/structs.py
msgspec/structs.pyi
msgspec/toml.py
msgspec/yaml.py
msgspec_m-0.19.3.dist-info/licenses/LICENSE
msgspec_m-0.19.3.dist-info/METADATA
msgspec_m-0.19.3.dist-info/WHEEL
msgspec_m-0.19.3.dist-info/top_level.txt
msgspec_m-0.19.3.dist-info/RECORD
